{
  "recipes": [
    {
      "type": "crafting_shaped",
      "name": "bakingdelight:amethyst_axe",
      "input": {
        "1": {
          "item": "minecraft:amethyst_shard",
          "count": 1
        },
        "2": {
          "item": "minecraft:amethyst_block",
          "count": 1
        },
        "4": {
          "item": "minecraft:amethyst_shard",
          "count": 1
        },
        "5": {
          "item": "minecraft:redstone_block",
          "count": 1
        },
        "8": {
          "item": "minecraft:iron_ingot",
          "count": 1
        }
      },
      "output": {
        "1": {
          "item": "bakingdelight:amethyst_axe",
          "count": 1,
          "nbt": "{Damage:0}"
        }
      }
    },
    {
      "type": "campfire_cooking",
      "name": "bakingdelight:smoking/roasted_squid_from_campfire_cooking",
      "input": {
        "1": {
          "item": "bakingdelight:squid",
          "count": 1
        }
      },
      "output": {
        "1": {
          "item": "bakingdelight:roasted_squid",
          "count": 1
        }
      },
      "experience": 0.35,
      "cookTime": 600
    },
    {
      "type": "smoking",
      "name": "bakingdelight:smoking/grilled_sausage_from_smoking",
      "input": {
        "1": {
          "item": "bakingdelight:sausage",
          "count": 1
        }
      },
      "output": {
        "1": {
          "item": "bakingdelight:grilled_sausage",
          "count": 1
        }
      },
      "experience": 0.35,
      "cookTime": 100
    },
    {
      "type": "blasting",
      "name": "bakingdelight:recycle/gold_nugget_from_blasting_whisk",
      "input": {
        "1": {
          "item": "bakingdelight:golden_whisk",
          "count": 1
        }
      },
      "output": {
        "1": {
          "item": "minecraft:gold_nugget",
          "count": 1
        }
      },
      "experience": 0.1,
      "cookTime": 100
    },
    {
      "type": "campfire_cooking",
      "name": "bakingdelight:smoking/grilled_sausage_from_campfire_cooking",
      "input": {
        "1": {
          "item": "bakingdelight:sausage",
          "count": 1
        }
      },
      "output": {
        "1": {
          "item": "bakingdelight:grilled_sausage",
          "count": 1
        }
      },
      "experience": 0.35,
      "cookTime": 600
    },
    {
      "type": "crafting_shapeless",
      "name": "bakingdelight:apple_cream",
      "input": {
        "1": {
          "item": "bakingdelight:cream",
          "count": 1
        },
        "2": {
          "item": "bakingdelight:apple_petal",
          "count": 1
        },
        "3": {
          "item": "bakingdelight:apple_petal",
          "count": 1
        }
      },
      "output": {
        "1": {
          "item": "bakingdelight:apple_cream",
          "count": 1
        }
      }
    },
    {
      "type": "crafting_shapeless",
      "name": "bakingdelight:truffle_egg_tart",
      "input": {
        "1": {
          "item": "bakingdelight:egg_tart",
          "count": 1
        },
        "2": {
          "item": "bakingdelight:black_truffle",
          "count": 1
        }
      },
      "output": {
        "1": {
          "item": "bakingdelight:truffle_egg_tart",
          "count": 1
        }
      }
    },
    {
      "type": "crafting_shaped",
      "name": "bakingdelight:stone_whisk_from_cobbled_deepslate",
      "input": {
        "1": {
          "item": "minecraft:cobbled_deepslate",
          "count": 1
        },
        "4": {
          "item": "minecraft:cobbled_deepslate_slab",
          "count": 1
        },
        "7": {
          "item": "minecraft:stick",
          "count": 1
        }
      },
      "output": {
        "1": {
          "item": "bakingdelight:stone_whisk",
          "count": 1,
          "nbt": "{Damage:0}"
        }
      }
    },
    {
      "type": "crafting_shaped",
      "name": "bakingdelight:golden_whisk",
      "input": {
        "1": {
          "item": "minecraft:gold_ingot",
          "count": 1
        },
        "4": {
          "item": "minecraft:gold_nugget",
          "count": 1
        },
        "7": {
          "item": "minecraft:stick",
          "count": 1
        }
      },
      "output": {
        "1": {
          "item": "bakingdelight:golden_whisk",
          "count": 1,
          "nbt": "{Damage:0}"
        }
      }
    },
    {
      "type": "crafting_shapeless",
      "name": "bakingdelight:pumpkin_cream",
      "input": {
        "1": {
          "item": "bakingdelight:cream",
          "count": 1
        },
        "2": {
          "tag": "c:foods/pumpkins",
          "count": 1
        },
        "3": {
          "tag": "c:foods/pumpkins",
          "count": 1
        }
      },
      "output": {
        "1": {
          "item": "bakingdelight:pumpkin_cream",
          "count": 1
        }
      }
    },
    {
      "type": "crafting_shaped",
      "name": "bakingdelight:amethyst_whisk",
      "input": {
        "1": {
          "item": "minecraft:amethyst_shard",
          "count": 1
        },
        "2": {
          "item": "minecraft:amethyst_shard",
          "count": 1
        },
        "3": {
          "item": "minecraft:amethyst_shard",
          "count": 1
        },
        "4": {
          "item": "minecraft:amethyst_shard",
          "count": 1
        },
        "5": {
          "item": "minecraft:redstone_block",
          "count": 1
        },
        "6": {
          "item": "minecraft:amethyst_shard",
          "count": 1
        },
        "8": {
          "item": "minecraft:iron_ingot",
          "count": 1
        }
      },
      "output": {
        "1": {
          "item": "bakingdelight:amethyst_whisk",
          "count": 1,
          "nbt": "{Damage:0}"
        }
      }
    },
    {
      "type": "smoking",
      "name": "bakingdelight:smoking/roasted_glow_squid_from_smoking",
      "input": {
        "1": {
          "item": "bakingdelight:glow_squid",
          "count": 1
        }
      },
      "output": {
        "1": {
          "item": "bakingdelight:roasted_glow_squid",
          "count": 1
        }
      },
      "experience": 0.35,
      "cookTime": 100
    },
    {
      "type": "crafting_shapeless",
      "name": "bakingdelight:cream",
      "input": {
        "1": {
          "item": "bakingdelight:cream_bucket",
          "count": 1
        },
        "2": {
          "item": "minecraft:bowl",
          "count": 1
        },
        "3": {
          "item": "minecraft:bowl",
          "count": 1
        },
        "4": {
          "item": "minecraft:bowl",
          "count": 1
        }
      },
      "output": {
        "1": {
          "item": "bakingdelight:cream",
          "count": 3
        }
      }
    },
    {
      "type": "crafting_shaped",
      "name": "bakingdelight:oven",
      "input": {
        "1": {
          "item": "minecraft:iron_ingot",
          "count": 1
        },
        "2": {
          "item": "minecraft:iron_ingot",
          "count": 1
        },
        "3": {
          "item": "minecraft:iron_ingot",
          "count": 1
        },
        "4": {
          "item": "minecraft:brick",
          "count": 1
        },
        "5": {
          "item": "minecraft:glass_pane",
          "count": 1
        },
        "6": {
          "item": "minecraft:brick",
          "count": 1
        },
        "7": {
          "item": "minecraft:brick",
          "count": 1
        },
        "8": {
          "item": "minecraft:iron_trapdoor",
          "count": 1
        },
        "9": {
          "item": "minecraft:brick",
          "count": 1
        }
      },
      "output": {
        "1": {
          "item": "bakingdelight:oven",
          "count": 1
        }
      }
    },
    {
      "type": "crafting_shapeless",
      "name": "bakingdelight:mashed_potato",
      "input": {
        "1": {
          "item": "bakingdelight:mashed_potato_block",
          "count": 1
        }
      },
      "output": {
        "1": {
          "item": "bakingdelight:mashed_potato",
          "count": 9
        }
      }
    },
    {
      "type": "crafting_shaped",
      "name": "bakingdelight:amethyst_knife",
      "input": {
        "3": {
          "item": "minecraft:amethyst_shard",
          "count": 1
        },
        "4": {
          "item": "minecraft:redstone",
          "count": 1
        },
        "5": {
          "item": "minecraft:amethyst_shard",
          "count": 1
        },
        "7": {
          "item": "minecraft:iron_ingot",
          "count": 1
        },
        "8": {
          "item": "minecraft:redstone",
          "count": 1
        }
      },
      "output": {
        "1": {
          "item": "bakingdelight:amethyst_knife",
          "count": 1,
          "nbt": "{Damage:0}"
        }
      }
    },
    {
      "type": "smelting",
      "name": "bakingdelight:smoking/grilled_sausage",
      "input": {
        "1": {
          "item": "bakingdelight:sausage",
          "count": 1
        }
      },
      "output": {
        "1": {
          "item": "bakingdelight:grilled_sausage",
          "count": 1
        }
      },
      "experience": 0.35,
      "cookTime": 200
    },
    {
      "type": "smelting",
      "name": "bakingdelight:smoking/roasted_glow_squid",
      "input": {
        "1": {
          "item": "bakingdelight:glow_squid",
          "count": 1
        }
      },
      "output": {
        "1": {
          "item": "bakingdelight:roasted_glow_squid",
          "count": 1
        }
      },
      "experience": 0.35,
      "cookTime": 200
    },
    {
      "type": "crafting_shapeless",
      "name": "bakingdelight:mousse_wip",
      "input": {
        "1": {
          "item": "minecraft:egg",
          "count": 1
        },
        "2": {
          "item": "bakingdelight:cream_bucket",
          "count": 1
        },
        "3": {
          "item": "minecraft:sugar",
          "count": 1
        },
        "4": {
          "item": "bakingdelight:butter",
          "count": 1
        },
        "5": {
          "item": "minecraft:wheat",
          "count": 1
        },
        "6": {
          "item": "minecraft:wheat",
          "count": 1
        }
      },
      "output": {
        "1": {
          "item": "bakingdelight:mousse_wip",
          "count": 12
        }
      }
    },
    {
      "type": "crafting_shapeless",
      "name": "bakingdelight:golden_apple_cream",
      "input": {
        "1": {
          "item": "bakingdelight:cream",
          "count": 1
        },
        "2": {
          "item": "minecraft:golden_apple",
          "count": 1
        }
      },
      "output": {
        "1": {
          "item": "bakingdelight:golden_apple_cream",
          "count": 1
        }
      }
    },
    {
      "type": "crafting_shaped",
      "name": "bakingdelight:amethyst_sword",
      "input": {
        "1": {
          "item": "minecraft:amethyst_block",
          "count": 1
        },
        "4": {
          "item": "minecraft:redstone_block",
          "count": 1
        },
        "7": {
          "item": "minecraft:iron_ingot",
          "count": 1
        }
      },
      "output": {
        "1": {
          "item": "bakingdelight:amethyst_sword",
          "count": 1,
          "nbt": "{Damage:0}"
        }
      }
    },
    {
      "type": "crafting_shaped",
      "name": "bakingdelight:copper_knife",
      "input": {
        "1": {
          "item": "minecraft:copper_block",
          "count": 1
        },
        "4": {
          "item": "minecraft:stick",
          "count": 1
        }
      },
      "output": {
        "1": {
          "item": "bakingdelight:copper_knife",
          "count": 1,
          "nbt": "{Damage:0}"
        }
      }
    },
    {
      "type": "smoking",
      "name": "bakingdelight:smoking/roasted_squid_from_smoking",
      "input": {
        "1": {
          "item": "bakingdelight:squid",
          "count": 1
        }
      },
      "output": {
        "1": {
          "item": "bakingdelight:roasted_squid",
          "count": 1
        }
      },
      "experience": 0.35,
      "cookTime": 100
    },
    {
      "type": "smithing_transform",
      "name": "bakingdelight:netherite_whisk_smithing",
      "input": {
        "1": {
          "item": "minecraft:netherite_upgrade_smithing_template",
          "count": 1
        },
        "2": {
          "item": "bakingdelight:diamond_whisk",
          "count": 1
        },
        "3": {
          "item": "minecraft:netherite_ingot",
          "count": 1
        }
      },
      "output": {
        "1": {
          "item": "bakingdelight:netherite_whisk",
          "count": 1,
          "nbt": "{Damage:0}"
        }
      }
    },
    {
      "type": "crafting_shaped",
      "name": "bakingdelight:diamond_whisk",
      "input": {
        "1": {
          "item": "minecraft:diamond",
          "count": 1
        },
        "4": {
          "item": "minecraft:amethyst_shard",
          "count": 1
        },
        "7": {
          "item": "minecraft:stick",
          "count": 1
        }
      },
      "output": {
        "1": {
          "item": "bakingdelight:diamond_whisk",
          "count": 1,
          "nbt": "{Damage:0}"
        }
      }
    },
    {
      "type": "crafting_shaped",
      "name": "bakingdelight:cherry_bomb",
      "input": {
        "2": {
          "item": "minecraft:gunpowder",
          "count": 1
        },
        "4": {
          "item": "minecraft:gunpowder",
          "count": 1
        },
        "5": {
          "item": "bakingdelight:cherry",
          "count": 1
        },
        "6": {
          "item": "minecraft:gunpowder",
          "count": 1
        },
        "8": {
          "item": "minecraft:gunpowder",
          "count": 1
        }
      },
      "output": {
        "1": {
          "item": "bakingdelight:cherry_bomb",
          "count": 1
        }
      }
    },
    {
      "type": "crafting_shapeless",
      "name": "bakingdelight:starch_sausage",
      "input": {
        "1": {
          "item": "bakingdelight:potato_starch",
          "count": 1
        },
        "2": {
          "item": "bakingdelight:sausage",
          "count": 1
        }
      },
      "output": {
        "1": {
          "item": "bakingdelight:starch_sausage",
          "count": 1
        }
      }
    },
    {
      "type": "crafting_shapeless",
      "name": "bakingdelight:mixed_dough",
      "input": {
        "1": {
          "item": "bakingdelight:potato_starch",
          "count": 1
        },
        "2": {
          "tag": "c:foods/doughs/wheat",
          "count": 1
        }
      },
      "output": {
        "1": {
          "item": "bakingdelight:mixed_dough",
          "count": 2
        }
      }
    },
    {
      "type": "crafting_shapeless",
      "name": "bakingdelight:sausage",
      "input": {
        "1": {
          "item": "bakingdelight:potato_starch",
          "count": 1
        },
        "2": {
          "tag": "c:foods/raw_meats/raw_pork",
          "count": 1
        }
      },
      "output": {
        "1": {
          "item": "bakingdelight:sausage",
          "count": 2
        }
      }
    },
    {
      "type": "blasting",
      "name": "bakingdelight:recycle/iron_nugget_from_blasting_whisk",
      "input": {
        "1": {
          "item": "bakingdelight:iron_whisk",
          "count": 1
        }
      },
      "output": {
        "1": {
          "item": "minecraft:iron_nugget",
          "count": 1
        }
      },
      "experience": 0.1,
      "cookTime": 100
    },
    {
      "type": "crafting_shapeless",
      "name": "bakingdelight:matcha_cream",
      "input": {
        "1": {
          "item": "bakingdelight:cream",
          "count": 1
        },
        "2": {
          "tag": "minecraft:leaves",
          "count": 1
        },
        "3": {
          "tag": "minecraft:leaves",
          "count": 1
        },
        "4": {
          "tag": "minecraft:leaves",
          "count": 1
        },
        "5": {
          "tag": "minecraft:leaves",
          "count": 1
        },
        "6": {
          "tag": "minecraft:leaves",
          "count": 1
        }
      },
      "output": {
        "1": {
          "item": "bakingdelight:matcha_cream",
          "count": 1
        }
      }
    },
    {
      "type": "crafting_shapeless",
      "name": "bakingdelight:pudding_wip_1",
      "input": {
        "1": {
          "item": "minecraft:egg",
          "count": 1
        },
        "2": {
          "item": "minecraft:milk_bucket",
          "count": 1
        },
        "3": {
          "item": "minecraft:sugar",
          "count": 1
        },
        "4": {
          "item": "bakingdelight:butter",
          "count": 1
        }
      },
      "output": {
        "1": {
          "item": "bakingdelight:pudding_wip_1",
          "count": 8
        }
      }
    },
    {
      "type": "crafting_shapeless",
      "name": "bakingdelight:cherry_cream",
      "input": {
        "1": {
          "item": "bakingdelight:cream",
          "count": 1
        },
        "2": {
          "item": "bakingdelight:cherry",
          "count": 1
        },
        "3": {
          "item": "bakingdelight:cherry",
          "count": 1
        }
      },
      "output": {
        "1": {
          "item": "bakingdelight:cherry_cream",
          "count": 1
        }
      }
    },
    {
      "type": "crafting_shaped",
      "name": "bakingdelight:freezer",
      "input": {
        "1": {
          "item": "minecraft:iron_ingot",
          "count": 1
        },
        "2": {
          "item": "minecraft:iron_ingot",
          "count": 1
        },
        "3": {
          "item": "minecraft:iron_ingot",
          "count": 1
        },
        "4": {
          "item": "minecraft:iron_ingot",
          "count": 1
        },
        "5": {
          "item": "minecraft:chest",
          "count": 1
        },
        "6": {
          "item": "minecraft:iron_ingot",
          "count": 1
        },
        "7": {
          "item": "minecraft:iron_ingot",
          "count": 1
        },
        "8": {
          "item": "minecraft:redstone",
          "count": 1
        },
        "9": {
          "item": "minecraft:iron_trapdoor",
          "count": 1
        }
      },
      "output": {
        "1": {
          "item": "bakingdelight:freezer",
          "count": 1
        }
      }
    },
    {
      "type": "crafting_shapeless",
      "name": "bakingdelight:black_pepper_dust",
      "input": {
        "1": {
          "tag": "c:crops/black_peppers",
          "count": 1
        }
      },
      "output": {
        "1": {
          "item": "bakingdelight:black_pepper_dust",
          "count": 1
        }
      }
    },
    {
      "type": "crafting_shaped",
      "name": "bakingdelight:wooden_whisk",
      "input": {
        "1": {
          "tag": "minecraft:planks",
          "count": 1
        },
        "4": {
          "tag": "minecraft:wooden_slabs",
          "count": 1
        },
        "7": {
          "item": "minecraft:stick",
          "count": 1
        }
      },
      "output": {
        "1": {
          "item": "bakingdelight:wooden_whisk",
          "count": 1,
          "nbt": "{Damage:0}"
        }
      }
    },
    {
      "type": "crafting_shaped",
      "name": "bakingdelight:mashed_potato_block",
      "input": {
        "1": {
          "item": "bakingdelight:mashed_potato",
          "count": 1
        },
        "2": {
          "item": "bakingdelight:mashed_potato",
          "count": 1
        },
        "3": {
          "item": "bakingdelight:mashed_potato",
          "count": 1
        },
        "4": {
          "item": "bakingdelight:mashed_potato",
          "count": 1
        },
        "5": {
          "item": "bakingdelight:mashed_potato",
          "count": 1
        },
        "6": {
          "item": "bakingdelight:mashed_potato",
          "count": 1
        },
        "7": {
          "item": "bakingdelight:mashed_potato",
          "count": 1
        },
        "8": {
          "item": "bakingdelight:mashed_potato",
          "count": 1
        },
        "9": {
          "item": "bakingdelight:mashed_potato",
          "count": 1
        }
      },
      "output": {
        "1": {
          "item": "bakingdelight:mashed_potato_block",
          "count": 1
        }
      }
    },
    {
      "type": "crafting_shaped",
      "name": "bakingdelight:copper_whisk",
      "input": {
        "1": {
          "item": "minecraft:copper_block",
          "count": 1
        },
        "4": {
          "item": "minecraft:copper_ingot",
          "count": 1
        },
        "7": {
          "item": "minecraft:stick",
          "count": 1
        }
      },
      "output": {
        "1": {
          "item": "bakingdelight:copper_whisk",
          "count": 1,
          "nbt": "{Damage:0}"
        }
      }
    },
    {
      "type": "crafting_shaped",
      "name": "bakingdelight:iron_whisk",
      "input": {
        "1": {
          "item": "minecraft:iron_ingot",
          "count": 1
        },
        "4": {
          "item": "minecraft:iron_nugget",
          "count": 1
        },
        "7": {
          "item": "minecraft:stick",
          "count": 1
        }
      },
      "output": {
        "1": {
          "item": "bakingdelight:iron_whisk",
          "count": 1,
          "nbt": "{Damage:0}"
        }
      }
    },
    {
      "type": "smelting",
      "name": "bakingdelight:recycle/gold_nugget_from_smelting_whisk",
      "input": {
        "1": {
          "item": "bakingdelight:golden_whisk",
          "count": 1
        }
      },
      "output": {
        "1": {
          "item": "minecraft:gold_nugget",
          "count": 1
        }
      },
      "experience": 0.1,
      "cookTime": 200
    },
    {
      "type": "crafting_shapeless",
      "name": "bakingdelight:chocolate_cream",
      "input": {
        "1": {
          "item": "bakingdelight:cream",
          "count": 1
        },
        "2": {
          "item": "minecraft:cocoa_beans",
          "count": 1
        },
        "3": {
          "item": "minecraft:cocoa_beans",
          "count": 1
        }
      },
      "output": {
        "1": {
          "item": "bakingdelight:chocolate_cream",
          "count": 1
        }
      }
    },
    {
      "type": "smelting",
      "name": "bakingdelight:recycle/iron_nugget_from_smelting_whisk",
      "input": {
        "1": {
          "item": "bakingdelight:iron_whisk",
          "count": 1
        }
      },
      "output": {
        "1": {
          "item": "minecraft:iron_nugget",
          "count": 1
        }
      },
      "experience": 0.1,
      "cookTime": 200
    },
    {
      "type": "crafting_shaped",
      "name": "bakingdelight:glass_bowl",
      "input": {
        "1": {
          "item": "minecraft:glass",
          "count": 1
        },
        "3": {
          "item": "minecraft:glass",
          "count": 1
        },
        "4": {
          "item": "minecraft:glass",
          "count": 1
        },
        "5": {
          "item": "minecraft:glass",
          "count": 1
        },
        "6": {
          "item": "minecraft:glass",
          "count": 1
        }
      },
      "output": {
        "1": {
          "item": "bakingdelight:glass_bowl",
          "count": 1
        }
      }
    },
    {
      "type": "crafting_shaped",
      "name": "bakingdelight:amethyst_hoe",
      "input": {
        "1": {
          "item": "minecraft:amethyst_shard",
          "count": 1
        },
        "2": {
          "item": "minecraft:amethyst_block",
          "count": 1
        },
        "5": {
          "item": "minecraft:redstone_block",
          "count": 1
        },
        "8": {
          "item": "minecraft:iron_ingot",
          "count": 1
        }
      },
      "output": {
        "1": {
          "item": "bakingdelight:amethyst_hoe",
          "count": 1,
          "nbt": "{Damage:0}"
        }
      }
    },
    {
      "type": "crafting_shaped",
      "name": "bakingdelight:amethyst_pickaxe",
      "input": {
        "1": {
          "item": "minecraft:amethyst_shard",
          "count": 1
        },
        "2": {
          "item": "minecraft:amethyst_block",
          "count": 1
        },
        "3": {
          "item": "minecraft:amethyst_shard",
          "count": 1
        },
        "5": {
          "item": "minecraft:redstone_block",
          "count": 1
        },
        "8": {
          "item": "minecraft:iron_ingot",
          "count": 1
        }
      },
      "output": {
        "1": {
          "item": "bakingdelight:amethyst_pickaxe",
          "count": 1,
          "nbt": "{Damage:0}"
        }
      }
    },
    {
      "type": "crafting_shaped",
      "name": "bakingdelight:amethyst_shovel",
      "input": {
        "1": {
          "item": "minecraft:amethyst_shard",
          "count": 1
        },
        "2": {
          "item": "minecraft:amethyst_block",
          "count": 1
        },
        "3": {
          "item": "minecraft:amethyst_shard",
          "count": 1
        },
        "4": {
          "item": "minecraft:amethyst_shard",
          "count": 1
        },
        "5": {
          "item": "minecraft:redstone_block",
          "count": 1
        },
        "6": {
          "item": "minecraft:amethyst_shard",
          "count": 1
        },
        "8": {
          "item": "minecraft:iron_ingot",
          "count": 1
        }
      },
      "output": {
        "1": {
          "item": "bakingdelight:amethyst_shovel",
          "count": 1,
          "nbt": "{Damage:0}"
        }
      }
    },
    {
      "type": "crafting_shaped",
      "name": "bakingdelight:stone_whisk_from_blackstone",
      "input": {
        "1": {
          "item": "minecraft:blackstone",
          "count": 1
        },
        "4": {
          "item": "minecraft:blackstone_slab",
          "count": 1
        },
        "7": {
          "item": "minecraft:stick",
          "count": 1
        }
      },
      "output": {
        "1": {
          "item": "bakingdelight:stone_whisk",
          "count": 1,
          "nbt": "{Damage:0}"
        }
      }
    },
    {
      "type": "crafting_shapeless",
      "name": "bakingdelight:butter_bread_slice",
      "input": {
        "1": {
          "item": "bakingdelight:butter",
          "count": 1
        },
        "2": {
          "item": "bakingdelight:bread_slice",
          "count": 1
        }
      },
      "output": {
        "1": {
          "item": "bakingdelight:butter_bread_slice",
          "count": 1
        }
      }
    },
    {
      "type": "smelting",
      "name": "bakingdelight:smoking/roasted_squid",
      "input": {
        "1": {
          "item": "bakingdelight:squid",
          "count": 1
        }
      },
      "output": {
        "1": {
          "item": "bakingdelight:roasted_squid",
          "count": 1
        }
      },
      "experience": 0.35,
      "cookTime": 200
    },
    {
      "type": "crafting_shaped",
      "name": "bakingdelight:stone_whisk_from_cobblestone",
      "input": {
        "1": {
          "item": "minecraft:cobblestone",
          "count": 1
        },
        "4": {
          "item": "minecraft:cobblestone_slab",
          "count": 1
        },
        "7": {
          "item": "minecraft:stick",
          "count": 1
        }
      },
      "output": {
        "1": {
          "item": "bakingdelight:stone_whisk",
          "count": 1,
          "nbt": "{Damage:0}"
        }
      }
    },
    {
      "type": "crafting_shaped",
      "name": "bakingdelight:kneading_stick",
      "input": {
        "3": {
          "item": "minecraft:stick",
          "count": 1
        },
        "5": {
          "tag": "minecraft:planks",
          "count": 1
        },
        "7": {
          "item": "minecraft:stick",
          "count": 1
        }
      },
      "output": {
        "1": {
          "item": "bakingdelight:kneading_stick",
          "count": 1,
          "nbt": "{Damage:0}"
        }
      }
    },
    {
      "type": "campfire_cooking",
      "name": "bakingdelight:smoking/roasted_glow_squid_from_campfire_cooking",
      "input": {
        "1": {
          "item": "bakingdelight:glow_squid",
          "count": 1
        }
      },
      "output": {
        "1": {
          "item": "bakingdelight:roasted_glow_squid",
          "count": 1
        }
      },
      "experience": 0.35,
      "cookTime": 600
    }
  ],
  "error": []
}